graph_ts/__init__.py
graph_ts/errors.py
graph_ts/mapping/__init__.py
graph_ts/mapping/edge_function.py
graph_ts/mapping/signal_function.py
graph_ts/misc/__init__.py
graph_ts/misc/utils.py
graph_ts/misc/visualization.py
graph_ts/simulation/__init__.py
graph_ts/simulation/dgcm.py
graph_ts/simulation/expert_sim.py
graph_ts/simulation/m_dgcm.py
graph_ts/simulation/m_graph.py
graph_ts/simulation/perturb.py
graph_ts/spz/__init__.py
graph_ts/spz/clinical_utils.py
graph_ts/structure/__init__.py
graph_ts/structure/dyn_graph.py
graph_ts/structure/edge_id.py
graphical_ts-0.3.dist-info/METADATA
graphical_ts-0.3.dist-info/WHEEL
graphical_ts-0.3.dist-info/top_level.txt
graphical_ts-0.3.dist-info/RECORD
