Metadata-Version: 2.1
Name: graphical-ts
Version: 0.3
Summary: Time series data simulation with underlying a graphical model
Author-email: Haixin Li <peterlai_0618@outlook.com>
Requires-Dist: numpy >=1.21
Requires-Dist: scipy >=1.7
Requires-Dist: networkx >=2.6
Requires-Dist: matplotlib >=3.4
Requires-Dist: pandas >=1.3
